assignment-3/1/b/b.v
module counter (input clk, input rst, input up, output reg[3:0] out);  
  initial
    out<= 0;

  always @ (posedge clk) begin  
    if (rst)  
      out <= 0;
    else if (out < 0) 
      out = 4'd15;    
    else if(up) 
      out <= out + 1;
    else
      out <= out -1 ;    
  end  
  
endmodule

assignment-3/1/b/tb.v
`include "b.v"

module tb;  

  reg clk;                     
  reg rst;                    
  wire [3:0] out; 
  reg up;            

  counter  c0 ( .clk (clk), .rst(rst), .up(up), .out (out));  
   
  always #5 clk = ~clk;  
  
  initial
    $monitor("out=%4b",out);
     
  initial begin
      $dumpfile("tb.vcd");
      $dumpvars(0, tb);
  end 

  initial begin  
    clk <= 0;  
    rst <= 0;
    up<=1;  
  
  
    #150   rst <= 1;  

    $display("Down");

    up<=0;  
  
    #10   rst <= 0;  
    #150   rst <= 1;
    #20 $finish;  
  end  
endmodule

assignment-3/1/b/tb.vcd
$date
	Thu Mar 23 14:21:20 2023
$end
$version
	Icarus Verilog
$end
$timescale
	1s
$end
$scope module tb $end
$var wire 4 ! out [3:0] $end
$var reg 1 " clk $end
$var reg 1 # rst $end
$var reg 1 $ up $end
$scope module c0 $end
$var wire 1 " clk $end
$var wire 1 # rst $end
$var wire 1 $ up $end
$var reg 4 % out [3:0] $end
$upscope $end
$upscope $end
$enddefinitions $end
#0
$dumpvars
b0 %
1$
0#
0"
b0 !
$end
#5
b1 !
b1 %
1"
#10
0"
#15
b10 !
b10 %
1"
#20
0"
#25
b11 !
b11 %
1"
#30
0"
#35
b100 !
b100 %
1"
#40
0"
#45
b101 !
b101 %
1"
#50
0"
#55
b110 !
b110 %
1"
#60
0"
#65
b111 !
b111 %
1"
#70
0"
#75
b1000 !
b1000 %
1"
#80
0"
#85
b1001 !
b1001 %
1"
#90
0"
#95
b1010 !
b1010 %
1"
#100
0"
#105
b1011 !
b1011 %
1"
#110
0"
#115
b1100 !
b1100 %
1"
#120
0"
#125
b1101 !
b1101 %
1"
#130
0"
#135
b1110 !
b1110 %
1"
#140
0"
#145
b1111 !
b1111 %
1"
#150
0$
1#
0"
#155
b0 !
b0 %
1"
#160
0#
0"
#165
b1111 !
b1111 %
1"
#170
0"
#175
b1110 !
b1110 %
1"
#180
0"
#185
b1101 !
b1101 %
1"
#190
0"
#195
b1100 !
b1100 %
1"
#200
0"
#205
b1011 !
b1011 %
1"
#210
0"
#215
b1010 !
b1010 %
1"
#220
0"
#225
b1001 !
b1001 %
1"
#230
0"
#235
b1000 !
b1000 %
1"
#240
0"
#245
b111 !
b111 %
1"
#250
0"
#255
b110 !
b110 %
1"
#260
0"
#265
b101 !
b101 %
1"
#270
0"
#275
b100 !
b100 %
1"
#280
0"
#285
b11 !
b11 %
1"
#290
0"
#295
b10 !
b10 %
1"
#300
0"
#305
b1 !
b1 %
1"
#310
1#
0"
#315
b0 !
b0 %
1"
