assignment-2/half_adder/half_adder.v
module half_adder(output cout,output s, input a, input b);

    and(cout,a,b);
    xor(s,a,b);

endmodule

assignment-2/full_adder_using_half_adder/full_adder.v
`include "half_adder.v"

module full_adder(output cout,output s, input a, input b, input c);

    wire cout1, cout2, sum1;

    half_adder h0(.cout(cout1), .s(sum1), .a(a), .b(b));
    half_adder h1(.cout(cout2), .s(s), .a(sum1), .b(c));
    or(cout,cout1,cout2);

endmodule

assignment-2/full_adder_using_half_adder/tb.v
`include "full_adder.v"
module tb;

    reg  a,b,c;
    wire  s,carr;

    full_adder f0(.cout(carr), .s(s), .a(a), .b(b), .c(c));

    initial begin

        $dumpfile("tb.vcd");
        $dumpvars(0, tb);
        $monitor("%0t, a=%0b,b=%0b,cin=%0b, sum=%0b,carry=%0b",$time,a,b,c,s,carr);

        {a,b,c} = 3'd0; #10
        {a,b,c} = 3'd1; #10
        {a,b,c} = 3'd2; #10
        {a,b,c} = 3'd3; #10
        {a,b,c} = 3'd4; #10
        {a,b,c} = 3'd5; #10
        {a,b,c} = 3'd6; #10
        {a,b,c} = 3'd7; #10

        $finish;

    end

endmodule

assignment-2/full_adder_using_half_adder/tb.vcd
$date
	Thu Feb 09 22:42:41 2023
$end
$version
	Icarus Verilog
$end
$timescale
	1s
$end
$scope module tb $end
$var wire 1 ! s $end
$var wire 1 " carr $end
$var reg 1 # a $end
$var reg 1 $ b $end
$var reg 1 % c $end
$scope module f0 $end
$var wire 1 # a $end
$var wire 1 $ b $end
$var wire 1 % c $end
$var wire 1 " cout $end
$var wire 1 & sum1 $end
$var wire 1 ! s $end
$var wire 1 ' cout2 $end
$var wire 1 ( cout1 $end
$scope module h0 $end
$var wire 1 # a $end
$var wire 1 $ b $end
$var wire 1 ( cout $end
$var wire 1 & s $end
$upscope $end
$scope module h1 $end
$var wire 1 & a $end
$var wire 1 % b $end
$var wire 1 ' cout $end
$var wire 1 ! s $end
$upscope $end
$upscope $end
$upscope $end
$enddefinitions $end
#0
$dumpvars
0(
0'
0&
0%
0$
0#
0"
0!
$end
#10
1!
1%
#20
1&
1!
1$
0%
#30
1"
1'
0!
1%
#40
0"
0'
1!
1#
0$
0%
#50
1"
1'
0!
1%
#60
1(
0&
0'
0!
1$
0%
#70
1!
1%
