assignment-2/4_2_encoder/4x2_encoder.v
module encoder(output a0,a1, input y3,y2,y1);

    assign a1 = y3 ? y2 ? 1'b1 : 1'b1 : y2 ? 1'b1 : 1'b0;
    assign a0 = y3 ? y1 ? 1'b1 : 1'b1 : y1 ? 1'b1 : 1'b0;

endmodule

assignment-2/4_2_encoder/tb.v
`include "4x2_encoder.v"

module tb;

    reg y3;
    reg y2;
    reg y1;

    wire a0;
    wire a1;

    encoder e0(.a0(a0), .a1(a1), .y3(y3), .y2(y2), .y1(y1));

    initial begin

        $dumpfile("tb.vcd");
        $dumpvars(0, tb);

        $monitor("%0t, a1=%0b,a0=%0b, y3=%0b,y2=%0b,y1=%0b",$time,a1,a0,y3,y2,y1);

        {y3,y2,y1} = 3'd0; #10
        {y3,y2,y1} = 3'd1; #10
        {y3,y2,y1} = 3'd2; #10
        {y3,y2,y1} = 3'd3; #10
        {y3,y2,y1} = 3'd4; #10
        {y3,y2,y1} = 3'd5; #10
        {y3,y2,y1} = 3'd6; #10
        {y3,y2,y1} = 3'd7; #10

        $finish;

    end

endmodule

assignment-2/4_2_encoder/tb.vcd
$date
	Tue Feb 07 15:47:49 2023
$end
$version
	Icarus Verilog
$end
$timescale
	1s
$end
$scope module tb $end
$var wire 1 ! a1 $end
$var wire 1 " a0 $end
$var reg 1 # y1 $end
$var reg 1 $ y2 $end
$var reg 1 % y3 $end
$scope module e0 $end
$var wire 1 # y1 $end
$var wire 1 $ y2 $end
$var wire 1 % y3 $end
$var wire 1 ! a1 $end
$var wire 1 " a0 $end
$upscope $end
$upscope $end
$enddefinitions $end
#0
$dumpvars
0%
0$
0#
0"
0!
$end
#10
1"
1#
#20
1!
0"
1$
0#
#30
1"
1#
#40
1%
0$
0#
#50
1#
#60
1$
0#
#70
1#
