assignment-2/prime_no/prime.v
module prime(output out, input a,b,c,d);

    wire out1,out2,out3,out4;
    wire nota, notb, notc, notd;

    not(nota,a);
    not(notb,b);
    not(notc,c);
    not(notd,d);
    and(out1,nota,notb,c);
    and(out2,notb,c,d);
    and(out3,b,notc,d);
    and(out4,nota,c,d);
    or(out,out1,out2,out3,out4);


endmodule

assignment-2/prime_no/tb.v
`include "prime.v"
module tb;

    reg [3:0] i;

    wire  out;

    prime p0(.out(out), .a(i[3]), .b(i[2]), .c(i[1]), .d(i[0]));

    initial begin

        $dumpfile("tb.vcd");
        $dumpvars(0, tb);
        $monitor("T= %0t, i=%b : out=%b",$time,i,out);

        i = 4'd0; #10
        i = 4'd1; #10
        i = 4'd2; #10
        i = 4'd3; #10
        i = 4'd4; #10
        i = 4'd5; #10
        i = 4'd6; #10
        i = 4'd7; #10
        i = 4'd8; #10
        i = 4'd9; #10
        i = 4'd10; #10
        i = 4'd11; #10
        i = 4'd12; #10
        i = 4'd13; #10
        i = 4'd14; #10
        i = 4'd15; #10

        $finish;

    end

endmodule

assignment-2/prime_no/tb.vcd
$date
	Tue Feb 07 09:12:28 2023
$end
$version
	Icarus Verilog
$end
$timescale
	1s
$end
$scope module tb $end
$var wire 1 ! out $end
$var reg 4 " i [3:0] $end
$scope module p0 $end
$var wire 1 # a $end
$var wire 1 $ b $end
$var wire 1 % c $end
$var wire 1 & d $end
$var wire 1 ' nota $end
$var wire 1 ( notb $end
$var wire 1 ) notc $end
$var wire 1 * notd $end
$var wire 1 ! out $end
$var wire 1 + out1 $end
$var wire 1 , out2 $end
$var wire 1 - out3 $end
$var wire 1 . out4 $end
$upscope $end
$upscope $end
$enddefinitions $end
#0
$dumpvars
0.
0-
0,
0+
1*
1)
1(
1'
0&
0%
0$
0#
b0 "
0!
$end
#10
0*
1&
b1 "
#20
1!
0)
1+
1*
1%
0&
b10 "
#30
0*
1,
1.
1&
b11 "
#40
0!
0(
1)
0+
1*
0,
0.
1$
0%
0&
b100 "
#50
1!
0*
1-
1&
b101 "
#60
0!
0)
1*
0-
1%
0&
b110 "
#70
1!
0*
1.
1&
b111 "
#80
0!
0'
1(
1)
1*
0.
1#
0$
0%
0&
b1000 "
#90
0*
1&
b1001 "
#100
0)
1*
1%
0&
b1010 "
#110
1!
0*
1,
1&
b1011 "
#120
0!
0(
1)
1*
0,
1$
0%
0&
b1100 "
#130
1!
0*
1-
1&
b1101 "
#140
0!
0)
1*
0-
1%
0&
b1110 "
#150
0*
1&
b1111 "
