assignment-2/mux_2x1/mux_2x1.v

module mux_2x1(output y,input a,b,sel);

    assign y = sel ? a : b;

endmodule

assignment-2/mux_2x1/mux_2x1_tb.v
`include "mux_2x1.v"

module mux_2x1_tb;

    reg a,b,sel;
    wire y;

    mux_2x1 DUT(.a(a), .b(b), .sel(sel), .y(y));

    initial begin
      
      $dumpfile("tb.vcd");
      $dumpvars(0, mux_2x1_tb);
      $monitor("T=%0t, a=%0b, b=%0b, sel=%0b, y=%0b",$time,a,b,sel,y);

          a=0; b=0; sel=0;
      #10 a=0; b=0; sel=1;
      #10 a=0; b=1; sel=0;
      #10 a=0; b=1; sel=1;
      #10 a=1; b=0; sel=0;
      #10 a=1; b=0; sel=1;
      #10 a=1; b=1; sel=0;
      #10 a=1; b=1; sel=1;

    end

endmodule

assignment-2/mux_2x1/tb.vcd
$date
	Wed Feb 08 11:11:21 2023
$end
$version
	Icarus Verilog
$end
$timescale
	1s
$end
$scope module mux_2x1_tb $end
$var wire 1 ! y $end
$var reg 1 " a $end
$var reg 1 # b $end
$var reg 1 $ sel $end
$scope module DUT $end
$var wire 1 " a $end
$var wire 1 # b $end
$var wire 1 $ sel $end
$var wire 1 ! y $end
$upscope $end
$upscope $end
$enddefinitions $end
#0
$dumpvars
0$
0#
0"
0!
$end
#10
1$
#20
1!
0$
1#
#30
0!
1$
#40
0$
0#
1"
#50
1!
1$
#60
0$
1#
#70
1$
