assignment-3/2/a.v
module shift_register_8bit(output reg [7:0]Q,input in,Clk,right,reset);
initial
begin
Q=8'b0;
end
always@(posedge Clk)
begin
if(reset==1)
Q=8'b0;
else if(right==1)//right shift
begin
Q=Q>>1;
Q[7]=in;
end
else if(right==0)//left shift
begin
Q=Q<<1;
Q[0]=in;
end
end
endmodule

assignment-3/2/tb.v
`include "a.v"
module shift_register_8bit_tb();
wire [7:0]Q;
reg reset,right,in;
reg Clk=0;
shift_register_8bit DUT(.Q(Q),.in(in),.Clk(Clk),.right(right),.reset(reset));
always
begin
#5 Clk=~Clk;
end 
  initial begin
      $dumpfile("tb.vcd");
      $dumpvars(0, shift_register_8bit_tb);
  end
initial
begin
right=0;in=1;
#10;right=0;in=0;
#10;right=0;in=0;
#10;right=0;in=0;
#10;right=0;in=0;
#10;right=0;in=0;
#10;right=0;in=0;
#10;right=0;in=0;
#10;right=0;in=0;
#10;right=0;in=0;
#100 $finish;
end
endmodule

assignment-3/2/tb.vcd
$date
	Thu Mar 23 16:33:34 2023
$end
$version
	Icarus Verilog
$end
$timescale
	1s
$end
$scope module shift_register_8bit_tb $end
$var wire 8 ! Q [7:0] $end
$var reg 1 " Clk $end
$var reg 1 # in $end
$var reg 1 $ reset $end
$var reg 1 % right $end
$scope module DUT $end
$var wire 1 " Clk $end
$var wire 1 # in $end
$var wire 1 $ reset $end
$var wire 1 % right $end
$var reg 8 & Q [7:0] $end
$upscope $end
$upscope $end
$enddefinitions $end
#0
$dumpvars
b0 &
0%
x$
1#
0"
b0 !
$end
#5
b1 !
b1 &
1"
#10
0"
0#
#15
b10 !
b10 &
1"
#20
0"
#25
b100 !
b100 &
1"
#30
0"
#35
b1000 !
b1000 &
1"
#40
0"
#45
b10000 !
b10000 &
1"
#50
0"
#55
b100000 !
b100000 &
1"
#60
0"
#65
b1000000 !
b1000000 &
1"
#70
0"
#75
b10000000 !
b10000000 &
1"
#80
0"
#85
b0 !
b0 &
1"
