assignment-3/1/d/d.v
module johnson(output reg [3:0] out, input  rst, input  right, input data, input clk);
    reg temp;

    initial
        out = 4'b1111;

    always @(posedge clk) begin

        if(rst) begin
            {out} = 0;
        end 

        else begin
           temp = out[0];
           out = out>>1;
           out[3] = ~temp;
        end 
        
    end
endmodule

assignment-3/1/d/tb.v
`include "d.v"

module tb;  

  reg clk;                     
  reg rst;                    
  wire [3:0] out;             

  johnson j0 (.out (out), .rst(rst), .clk(clk));   
   
  always #5 clk = ~clk;  
  
  initial
    $monitor("T=%0t, out=%4b",$time,out);
  
  initial begin
      $dumpfile("tb.vcd");
      $dumpvars(0, tb);
  end
   
  initial begin  
    clk <= 0;
    rst <= 0;

    #80 $finish;  
  end  
endmodule

assignment-3/1/d/tb.vcd
$date
	Thu Mar 23 14:39:00 2023
$end
$version
	Icarus Verilog
$end
$timescale
	1s
$end
$scope module tb $end
$var wire 4 ! out [3:0] $end
$var reg 1 " clk $end
$var reg 1 # rst $end
$scope module j0 $end
$var wire 1 " clk $end
$var wire 1 $ data $end
$var wire 1 % right $end
$var wire 1 # rst $end
$var reg 4 & out [3:0] $end
$var reg 1 ' temp $end
$upscope $end
$upscope $end
$enddefinitions $end
#0
$dumpvars
x'
b1111 &
z%
z$
0#
0"
b1111 !
$end
#5
b111 !
b111 &
1'
1"
#10
0"
#15
b11 !
b11 &
1"
#20
0"
#25
b1 !
b1 &
1"
#30
0"
#35
b0 !
b0 &
1"
#40
0"
#45
b1000 !
b1000 &
0'
1"
#50
0"
#55
b1100 !
b1100 &
1"
#60
0"
#65
b1110 !
b1110 &
1"
#70
0"
#75
b1111 !
b1111 &
1"
